trivoreid/__init__.py
trivoreid/client.py
trivoreid/exceptions.py
trivoreid/models/__init__.py
trivoreid/models/access_right.py
trivoreid/models/accesscontrol.py
trivoreid/models/authorisation.py
trivoreid/models/contact.py
trivoreid/models/contract.py
trivoreid/models/datastorage.py
trivoreid/models/email.py
trivoreid/models/enterprise.py
trivoreid/models/groups.py
trivoreid/models/invite.py
trivoreid/models/locationsite.py
trivoreid/models/misc.py
trivoreid/models/mydata.py
trivoreid/models/namespace.py
trivoreid/models/objectid.py
trivoreid/models/page.py
trivoreid/models/pass_requirements.py
trivoreid/models/paycard.py
trivoreid/models/products.py
trivoreid/models/profile.py
trivoreid/models/sales.py
trivoreid/models/sms.py
trivoreid/models/subscription.py
trivoreid/models/target.py
trivoreid/models/user.py
trivoreid/models/wallet.py
trivoreid/oidc/__init__.py
trivoreid/oidc/oidc_client.py
trivoreid/oidc/oidc_user.py
trivoreid/services/__init__.py
trivoreid/services/access_control_service.py
trivoreid/services/access_right_service.py
trivoreid/services/authorisation_service.py
trivoreid/services/contact_service.py
trivoreid/services/contract_service.py
trivoreid/services/datastorage_service.py
trivoreid/services/email_service.py
trivoreid/services/group_service.py
trivoreid/services/locationsites_service.py
trivoreid/services/mydata_service.py
trivoreid/services/namespace_service.py
trivoreid/services/paycard_service.py
trivoreid/services/product_service.py
trivoreid/services/profile_service.py
trivoreid/services/sales_service.py
trivoreid/services/sms_service.py
trivoreid/services/subscription_service.py
trivoreid/services/target_service.py
trivoreid/services/user_service.py
trivoreid/services/wallet_service.py
trivoreid/utils/__init__.py
trivoreid/utils/criteria.py
trivoreid/utils/service_utils.py
trivoreid_extension-1.0.9.dist-info/LICENSE
trivoreid_extension-1.0.9.dist-info/METADATA
trivoreid_extension-1.0.9.dist-info/WHEEL
trivoreid_extension-1.0.9.dist-info/top_level.txt
trivoreid_extension-1.0.9.dist-info/RECORD
