Metadata-Version: 2.1
Name: trivoreid-extension
Version: 1.0.9
Summary: Wrapper Extension for TrivoreID SDK API
Home-page: UNKNOWN
Author: Anastasia Gromova
Author-email: id-client-sdk@trivore.com
Maintainer: Anastasia Gromova
Maintainer-email: id-client-sdk@trivore.com
License: Apache 2.0
Platform: UNKNOWN
